pypi_search/__init__.py
pypi_search/__main__.py
pypi_search/arg_parser.py
pypi_search/log.py
pypi_search/main.py
pypi_search/search.py
pypi_search/utils.py
pypi_search-2.0.dist-info/LICENSE
pypi_search-2.0.dist-info/METADATA
pypi_search-2.0.dist-info/WHEEL
pypi_search-2.0.dist-info/entry_points.txt
pypi_search-2.0.dist-info/top_level.txt
pypi_search-2.0.dist-info/RECORD
