Metadata-Version: 2.1
Name: pypi-search
Version: 2.0
Summary: Get Information on Python Packages From PyPI
Home-page: https://github.com/asadmoosvi/pypi-search
Author: Asad Moosvi
Author-email: moosvi.asad@gmail.com
License: MIT
Classifier: Programming Language :: Python :: 3
Classifier: License :: OSI Approved :: MIT License
Classifier: Operating System :: OS Independent
Requires-Python: >=3.6
License-File: LICENSE
